{
  "content": [
    {
      "content": null,
      "created": "2024-10-07T01:51:27.128592Z",
      "format": null,
      "last_modified": "2024-10-07T01:51:04.924151Z",
      "mimetype": null,
      "name": "data-science-python-exceptions.ipynb",
      "path": "data-science-python-exceptions.ipynb",
      "size": 12059,
      "type": "notebook",
      "writable": true
    },
    {
      "content": null,
      "created": "2024-10-07T01:51:27.130593Z",
      "format": null,
      "last_modified": "2024-10-07T01:51:04.932152Z",
      "mimetype": null,
      "name": "data-science-python-iterables.ipynb",
      "path": "data-science-python-iterables.ipynb",
      "size": 68475,
      "type": "notebook",
      "writable": true
    },
    {
      "content": null,
      "created": "2024-10-07T01:51:27.131593Z",
      "format": null,
      "last_modified": "2024-10-07T01:51:04.935152Z",
      "mimetype": null,
      "name": "data-science-python-math.ipynb",
      "path": "data-science-python-math.ipynb",
      "size": 28206,
      "type": "notebook",
      "writable": true
    },
    {
      "content": null,
      "created": "2024-10-07T01:51:27.131593Z",
      "format": null,
      "last_modified": "2024-10-07T01:51:04.938152Z",
      "mimetype": null,
      "name": "data-science-python-plotting.ipynb",
      "path": "data-science-python-plotting.ipynb",
      "size": 142401,
      "type": "notebook",
      "writable": true
    },
    {
      "content": null,
      "created": "2024-10-07T01:51:27.133593Z",
      "format": null,
      "last_modified": "2024-10-07T01:51:04.943152Z",
      "mimetype": null,
      "name": "data-science-python-types.ipynb",
      "path": "data-science-python-types.ipynb",
      "size": 29250,
      "type": "notebook",
      "writable": true
    },
    {
      "content": null,
      "created": "2024-10-07T01:51:27.129593Z",
      "format": null,
      "last_modified": "2024-10-07T01:51:04.928151Z",
      "mimetype": null,
      "name": "data-science-python-functions.ipynb",
      "path": "data-science-python-functions.ipynb",
      "size": 37305,
      "type": "notebook",
      "writable": true
    },
    {
      "content": null,
      "created": "2024-10-07T01:51:27.126593Z",
      "format": null,
      "last_modified": "2024-10-07T01:51:04.919151Z",
      "mimetype": null,
      "name": "data-science-python-advanced-np-pd.ipynb",
      "path": "data-science-python-advanced-np-pd.ipynb",
      "size": 114768,
      "type": "notebook",
      "writable": true
    },
    {
      "content": null,
      "created": "2024-10-07T01:51:27.130593Z",
      "format": null,
      "last_modified": "2024-10-07T01:51:04.933151Z",
      "mimetype": null,
      "name": "data-science-python-loops.ipynb",
      "path": "data-science-python-loops.ipynb",
      "size": 45142,
      "type": "notebook",
      "writable": true
    },
    {
      "content": null,
      "created": "2024-10-07T01:51:27.132593Z",
      "format": null,
      "last_modified": "2024-10-07T01:51:04.940152Z",
      "mimetype": null,
      "name": "data-science-python-subprocess.ipynb",
      "path": "data-science-python-subprocess.ipynb",
      "size": 23107,
      "type": "notebook",
      "writable": true
    },
    {
      "content": null,
      "created": "2024-10-07T01:51:27.133593Z",
      "format": null,
      "last_modified": "2024-10-07T01:51:04.945152Z",
      "mimetype": null,
      "name": "data-science-python-typing.ipynb",
      "path": "data-science-python-typing.ipynb",
      "size": 134930,
      "type": "notebook",
      "writable": true
    },
    {
      "content": null,
      "created": "2024-10-07T01:51:27.127593Z",
      "format": null,
      "last_modified": "2024-10-07T01:51:04.921151Z",
      "mimetype": null,
      "name": "data-science-python-basics.ipynb",
      "path": "data-science-python-basics.ipynb",
      "size": 159870,
      "type": "notebook",
      "writable": true
    },
    {
      "content": null,
      "created": "2024-10-07T01:51:27.128592Z",
      "format": null,
      "last_modified": "2024-10-07T01:51:04.925151Z",
      "mimetype": null,
      "name": "data-science-python-files.ipynb",
      "path": "data-science-python-files.ipynb",
      "size": 43044,
      "type": "notebook",
      "writable": true
    },
    {
      "content": null,
      "created": "2024-10-07T01:51:27.131593Z",
      "format": null,
      "last_modified": "2024-10-07T01:51:04.937152Z",
      "mimetype": null,
      "name": "data-science-python-multiprocessing.ipynb",
      "path": "data-science-python-multiprocessing.ipynb",
      "size": 44061,
      "type": "notebook",
      "writable": true
    },
    {
      "content": null,
      "created": "2024-10-07T01:51:27.132593Z",
      "format": null,
      "last_modified": "2024-10-07T01:51:04.942152Z",
      "mimetype": null,
      "name": "data-science-python-testing.ipynb",
      "path": "data-science-python-testing.ipynb",
      "size": 22271,
      "type": "notebook",
      "writable": true
    },
    {
      "content": null,
      "created": "2024-10-07T01:51:27.128592Z",
      "format": null,
      "last_modified": "2024-10-07T01:51:04.927151Z",
      "mimetype": null,
      "name": "data-science-python-flow.ipynb",
      "path": "data-science-python-flow.ipynb",
      "size": 42897,
      "type": "notebook",
      "writable": true
    },
    {
      "content": null,
      "created": "2024-10-07T01:51:27.127593Z",
      "format": null,
      "last_modified": "2024-10-07T01:51:04.922151Z",
      "mimetype": null,
      "name": "data-science-python-basics-recap.ipynb",
      "path": "data-science-python-basics-recap.ipynb",
      "size": 30860,
      "type": "notebook",
      "writable": true
    },
    {
      "content": null,
      "created": "2024-10-07T01:51:27.129593Z",
      "format": null,
      "last_modified": "2024-10-07T01:51:04.930151Z",
      "mimetype": null,
      "name": "data-science-python-glob.ipynb",
      "path": "data-science-python-glob.ipynb",
      "size": 9468,
      "type": "notebook",
      "writable": true
    }
  ],
  "created": "2024-10-07T01:51:27.133593Z",
  "format": "json",
  "last_modified": "2024-10-07T01:51:27.133593Z",
  "mimetype": null,
  "name": "",
  "path": "",
  "size": null,
  "type": "directory",
  "writable": true
}